factorial/__init__.py
factorial/factorial.py
factorial/setup.py
factorial/test.py
factorialalexmclean-1.0.dist-info/METADATA
factorialalexmclean-1.0.dist-info/WHEEL
factorialalexmclean-1.0.dist-info/top_level.txt
factorialalexmclean-1.0.dist-info/RECORD
