Metadata-Version: 2.1
Name: factorialalexmclean
Version: 1.0
Summary: A Singly Linked List Data structure
Author: Alex McLean
Author-email: alexander.mclean@ucalgary.ca,
License: UNKNOWN
Platform: UNKNOWN
